mcp_server_webcrawl/__init__.py
mcp_server_webcrawl/main.py
mcp_server_webcrawl/settings.py
mcp_server_webcrawl/crawlers/__init__.py
mcp_server_webcrawl/crawlers/archivebox/__init__.py
mcp_server_webcrawl/crawlers/archivebox/adapter.py
mcp_server_webcrawl/crawlers/archivebox/crawler.py
mcp_server_webcrawl/crawlers/archivebox/tests.py
mcp_server_webcrawl/crawlers/base/__init__.py
mcp_server_webcrawl/crawlers/base/adapter.py
mcp_server_webcrawl/crawlers/base/api.py
mcp_server_webcrawl/crawlers/base/crawler.py
mcp_server_webcrawl/crawlers/base/indexed.py
mcp_server_webcrawl/crawlers/base/tests.py
mcp_server_webcrawl/crawlers/httrack/__init__.py
mcp_server_webcrawl/crawlers/httrack/adapter.py
mcp_server_webcrawl/crawlers/httrack/crawler.py
mcp_server_webcrawl/crawlers/httrack/tests.py
mcp_server_webcrawl/crawlers/interrobot/__init__.py
mcp_server_webcrawl/crawlers/interrobot/adapter.py
mcp_server_webcrawl/crawlers/interrobot/crawler.py
mcp_server_webcrawl/crawlers/interrobot/tests.py
mcp_server_webcrawl/crawlers/katana/__init__.py
mcp_server_webcrawl/crawlers/katana/adapter.py
mcp_server_webcrawl/crawlers/katana/crawler.py
mcp_server_webcrawl/crawlers/katana/tests.py
mcp_server_webcrawl/crawlers/siteone/__init__.py
mcp_server_webcrawl/crawlers/siteone/adapter.py
mcp_server_webcrawl/crawlers/siteone/crawler.py
mcp_server_webcrawl/crawlers/siteone/tests.py
mcp_server_webcrawl/crawlers/warc/__init__.py
mcp_server_webcrawl/crawlers/warc/adapter.py
mcp_server_webcrawl/crawlers/warc/crawler.py
mcp_server_webcrawl/crawlers/warc/tests.py
mcp_server_webcrawl/crawlers/wget/__init__.py
mcp_server_webcrawl/crawlers/wget/adapter.py
mcp_server_webcrawl/crawlers/wget/crawler.py
mcp_server_webcrawl/crawlers/wget/tests.py
mcp_server_webcrawl/extras/__init__.py
mcp_server_webcrawl/extras/markdown.py
mcp_server_webcrawl/extras/regex.py
mcp_server_webcrawl/extras/snippets.py
mcp_server_webcrawl/extras/thumbnails.py
mcp_server_webcrawl/extras/xpath.py
mcp_server_webcrawl-0.15.0.dist-info/licenses/LICENSE
mcp_server_webcrawl-0.15.0.dist-info/METADATA
mcp_server_webcrawl-0.15.0.dist-info/WHEEL
mcp_server_webcrawl-0.15.0.dist-info/entry_points.txt
mcp_server_webcrawl-0.15.0.dist-info/top_level.txt
mcp_server_webcrawl-0.15.0.dist-info/RECORD
