Metadata-Version: 2.4
Name: mcp-server-webcrawl
Version: 0.15.0
Summary: MCP server for search and retrieval of web crawler content
Author: Ben Caulfield
Project-URL: Homepage, https://pragmar.com/mcp-server-webcrawl/
Classifier: Programming Language :: Python :: 3
Classifier: Operating System :: OS Independent
Classifier: License :: OSI Approved :: Mozilla Public License 2.0 (MPL 2.0)
Requires-Python: >=3.10
License-File: LICENSE
Requires-Dist: mcp>=1.3.0
Requires-Dist: lxml>=4.6.0
Requires-Dist: Pillow>=9.0.0
Requires-Dist: aiohttp>=3.8.0
Requires-Dist: warcio>=1.7.0
Requires-Dist: ply==3.11
Requires-Dist: windows-curses; sys_platform == "win32"
Dynamic: license-file
